[
  {"slug":"berlin","insolationKwhM2":1120,"specificYieldRange":"900–1020","storageAdoptionHint":"Hohe Abendlast → 5–10 kWh Speicher steigert Eigenverbrauch deutlich","gridProcessNote":"Netzbetreiber Freigabe ~4–8 Wochen","shadingRisk":"medium","roofMixNote":"Flachdachanteil & Altbaudächer mit Aufbauten"},
  {"slug":"potsdam","insolationKwhM2":1140,"specificYieldRange":"920–1040","storageAdoptionHint":"Eigenheime mit Tageslast – 5–8 kWh Speicher oft optimal","gridProcessNote":"Relativ zügig (3–6 Wochen)","shadingRisk":"low","roofMixNote":"Sattel- & Walmdächer überwiegen"},
  {"slug":"brandenburg","insolationKwhM2":1150,"specificYieldRange":"930–1050","storageAdoptionHint":"Ländlich: Größere Dachflächen → Speicher 8–12 kWh","gridProcessNote":"Bearbeitung variiert regional 4–9 Wochen","shadingRisk":"low","roofMixNote":"Weitläufige Sattel-/Scheunendächer"},
  {"slug":"hamburg","insolationKwhM2":1050,"specificYieldRange":"880–990","storageAdoptionHint":"Wetterwechsel → Speicher glättet Erträge","gridProcessNote":"Teilweise länger (6–10 Wochen)","shadingRisk":"medium","roofMixNote":"Backstein-Dächer, teils Mansard"},
  {"slug":"muenchen","insolationKwhM2":1200,"specificYieldRange":"950–1080","storageAdoptionHint":"Gute Strahlung – Speicher erhöht Autarkie","gridProcessNote":"Stabil 4–7 Wochen","shadingRisk":"low","roofMixNote":"Steildächer mit Südausrichtung häufig"},
  {"slug":"koeln","insolationKwhM2":1090,"specificYieldRange":"900–1010","storageAdoptionHint":"Abendspitzen → 6–9 kWh Speicher gängig","gridProcessNote":"5–8 Wochen","shadingRisk":"medium","roofMixNote":"Reihenhaus-Strukturen, teils Verschattung"},
  {"slug":"stuttgart","insolationKwhM2":1180,"specificYieldRange":"940–1070","storageAdoptionHint":"Hoher Eigenverbrauch durch E-Mobilitätspotenzial","gridProcessNote":"4–7 Wochen","shadingRisk":"medium","roofMixNote":"Hanglagen & differenzierte Dachneigungen"},
  {"slug":"frankfurt","insolationKwhM2":1130,"specificYieldRange":"920–1040","storageAdoptionHint":"Büro-/Home-Office Mischprofile → Speicher 7–10 kWh","gridProcessNote":"5–8 Wochen","shadingRisk":"medium","roofMixNote":"Mischung Flach- & Steildach"},
  {"slug":"bremen","insolationKwhM2":1030,"specificYieldRange":"860–970","storageAdoptionHint":"Höhere Bewölkung – Speicher puffert Ertragsschwankung","gridProcessNote":"6–9 Wochen","shadingRisk":"medium","roofMixNote":"Ziegel Dächer, teils Gauben"},
  {"slug":"duesseldorf","insolationKwhM2":1100,"specificYieldRange":"900–1020","storageAdoptionHint":"Abendlast & Wärmepumpen-Trend → Speicher sinnvoll","gridProcessNote":"5–8 Wochen","shadingRisk":"medium","roofMixNote":"Reihenstruktur, mittlere Verschattung"},
  {"slug":"essen","insolationKwhM2":1080,"specificYieldRange":"890–1000","storageAdoptionHint":"Lastverschiebung wegen Berufspendlern","gridProcessNote":"6–9 Wochen","shadingRisk":"medium","roofMixNote":"Dichte Bebauung, Gauben"},
  {"slug":"dresden","insolationKwhM2":1170,"specificYieldRange":"940–1060","storageAdoptionHint":"Guter Ertrag → Speicher erhöht Autarkie auf >50%","gridProcessNote":"4–7 Wochen","shadingRisk":"low","roofMixNote":"Steildächer häufig günstig ausgerichtet"},
  {"slug":"dortmund","insolationKwhM2":1090,"specificYieldRange":"900–1010","storageAdoptionHint":"Familienprofile → Speicher 6–8 kWh","gridProcessNote":"6–9 Wochen","shadingRisk":"medium","roofMixNote":"Reihenhäuser mit Nachbarverschattung"},
  {"slug":"mannheim","insolationKwhM2":1190,"specificYieldRange":"950–1080","storageAdoptionHint":"Gute Strahlung + Gewerbe Dächer","gridProcessNote":"4–6 Wochen","shadingRisk":"low","roofMixNote":"Industrie-/Flachdächer & Wohnmix"},
  {"slug":"bonn","insolationKwhM2":1100,"specificYieldRange":"900–1010","storageAdoptionHint":"Pendler + Abendlast → Speicher 7 kWh","gridProcessNote":"5–8 Wochen","shadingRisk":"medium","roofMixNote":"Steildächer mit Gaubenanteil"},
  {"slug":"kiel","insolationKwhM2":1040,"specificYieldRange":"870–980","storageAdoptionHint":"Küstenschwankungen – 6–8 kWh Speicher glättet Last","gridProcessNote":"Teilweise wetterbedingte Verzögerungen 6–10 Wochen","shadingRisk":"low","roofMixNote":"Flach geneigte Ziegel- & Satteldächer, selten Verschattung"},
  {"slug":"rostock","insolationKwhM2":1035,"specificYieldRange":"865–975","storageAdoptionHint":"Seewind & diffuse Einstrahlung – Speicher stabilisiert Abendlast","gridProcessNote":"Ähnlich Kiel 6–10 Wochen","shadingRisk":"low","roofMixNote":"Geringe Verschattung, maritime Witterungseinflüsse"},
  {"slug":"luebeck","insolationKwhM2":1055,"specificYieldRange":"880–990","storageAdoptionHint":"Wechselhafte Bewölkung → 6–9 kWh Speicher","gridProcessNote":"6–9 Wochen","shadingRisk":"medium","roofMixNote":"Altstadtnähe teils Gauben / Verschattung"},
  {"slug":"oldenburg","insolationKwhM2":1060,"specificYieldRange":"885–995","storageAdoptionHint":"Gute Kombi mit Wärmepumpe (Lastverschiebung)","gridProcessNote":"5–8 Wochen","shadingRisk":"medium","roofMixNote":"Durchmischte Sattel-/Walmdächer, Bepflanzung"},
  {"slug":"darmstadt","insolationKwhM2":1155,"specificYieldRange":"930–1050","storageAdoptionHint":"Hohe Büro-/Homeoffice-Dichte → Speicher 7–9 kWh","gridProcessNote":"4–7 Wochen","shadingRisk":"medium","roofMixNote":"Stadtrand größere Flächen, Innenstadt Gauben"},
  {"slug":"kassel","insolationKwhM2":1110,"specificYieldRange":"905–1015","storageAdoptionHint":"Hügelprofil → Teilverschattung ausgleichen mit Speicher","gridProcessNote":"5–8 Wochen","shadingRisk":"medium","roofMixNote":"Hanglagen & Mischdächer"},
  {"slug":"wiesbaden","insolationKwhM2":1145,"specificYieldRange":"925–1045","storageAdoptionHint":"Weinberg-Nähe: Diffuse Reflexion gering positiv","gridProcessNote":"4–7 Wochen","shadingRisk":"low","roofMixNote":"Große Pfannendächer, geringere Verschattung"},
  {"slug":"augsburg","insolationKwhM2":1195,"specificYieldRange":"950–1090","storageAdoptionHint":"Hohe Einstrahlung – Speicher erhöht Eigenverbrauch >55%","gridProcessNote":"4–6 Wochen","shadingRisk":"low","roofMixNote":"Viele gut ausgerichtete Steildächer"},
  {"slug":"ingolstadt","insolationKwhM2":1185,"specificYieldRange":"945–1085","storageAdoptionHint":"Industrie/Automotive Lastprofile → Speicher Lastverschiebung","gridProcessNote":"4–6 Wochen","shadingRisk":"low","roofMixNote":"Gewerbe Flachdächer + Wohnsteildächer"},
  {"slug":"regensburg","insolationKwhM2":1175,"specificYieldRange":"940–1075","storageAdoptionHint":"Konstante Einstrahlung – 7–9 kWh Speicher sinnvoll","gridProcessNote":"4–6 Wochen","shadingRisk":"low","roofMixNote":"Historische Dächer + Neubau Mischstruktur"},
  {"slug":"wuerzburg","insolationKwhM2":1165,"specificYieldRange":"935–1065","storageAdoptionHint":"Weinberge & Reflexion – moderat höherer spezifischer Ertrag","gridProcessNote":"4–6 Wochen","shadingRisk":"low","roofMixNote":"Steildächer mit klaren Südfeldern"},
  {"slug":"erfurt","insolationKwhM2":1125,"specificYieldRange":"905–1020","storageAdoptionHint":"Kontinentale Temperaturspannen – Speicher balanciert Winter/Über-gang","gridProcessNote":"5–8 Wochen","shadingRisk":"medium","roofMixNote":"Mischung Sattel-/Walmdächer, teils Verschattung"},
  {"slug":"jena","insolationKwhM2":1135,"specificYieldRange":"915–1030","storageAdoptionHint":"Forschungs-/Technologiehaushalte mit höherem Tagesverbrauch → Speicher","gridProcessNote":"5–8 Wochen","shadingRisk":"medium","roofMixNote":"Hanglagen & Vegetation (punktuelle Verschattung)"},
  {"slug":"magdeburg","insolationKwhM2":1140,"specificYieldRange":"920–1035","storageAdoptionHint":"Stabile Einstrahlung – Speicher 6–8 kWh typischer Sweetspot","gridProcessNote":"5–7 Wochen","shadingRisk":"low","roofMixNote":"Weitläufige Dächer mit wenig Verschattung"},
  {"slug":"heidelberg","insolationKwhM2":1180,"specificYieldRange":"945–1070","storageAdoptionHint":"Akademische Nutzung + EV-Adoption → Speicher 7–9 kWh","gridProcessNote":"4–6 Wochen","shadingRisk":"medium","roofMixNote":"Altbau + Forschungseinrichtungen, unterschiedliche Neigungen"},
  {"slug":"ulm","insolationKwhM2":1170,"specificYieldRange":"940–1065","storageAdoptionHint":"Kombination mit Wärmepumpe verbreitet → Speicher Synergie","gridProcessNote":"4–6 Wochen","shadingRisk":"low","roofMixNote":"Viele frei stehende Einfamilienhäuser"}
  ,{"slug":"bielefeld","insolationKwhM2":1085,"specificYieldRange":"890–1005","storageAdoptionHint":"Pendlerprofile → Speicher 6–8 kWh für Abendlast","gridProcessNote":"6–9 Wochen","shadingRisk":"medium","roofMixNote":"Reihenhäuser + einzelne Verschattungen durch Bäume"}
  ,{"slug":"braunschweig","insolationKwhM2":1095,"specificYieldRange":"900–1015","storageAdoptionHint":"Stabile Grundlast – Speicher 6–8 kWh effizient","gridProcessNote":"5–8 Wochen","shadingRisk":"medium","roofMixNote":"Ziegel Steildächer, moderate Gauben"}
  ,{"slug":"freiburg","insolationKwhM2":1250,"specificYieldRange":"980–1120","storageAdoptionHint":"Sehr hohe Einstrahlung → Speicher >8 kWh maximiert Autarkie","gridProcessNote":"4–6 Wochen","shadingRisk":"low","roofMixNote":"Viele gut ausgerichtete Süddächer"}
  ,{"slug":"hannover","insolationKwhM2":1065,"specificYieldRange":"880–995","storageAdoptionHint":"Wechselhafte Bewölkung → Speicher glättet Tagesprofil","gridProcessNote":"6–9 Wochen","shadingRisk":"medium","roofMixNote":"Reihen- & Mehrfamilienstrukturen"}
  ,{"slug":"karlsruhe","insolationKwhM2":1210,"specificYieldRange":"960–1090","storageAdoptionHint":"Hohe Einstrahlung – Speicher 7–9 kWh üblich","gridProcessNote":"4–6 Wochen","shadingRisk":"low","roofMixNote":"Steildächer mit klaren Südfeldern"}
  ,{"slug":"leipzig","insolationKwhM2":1120,"specificYieldRange":"900–1030","storageAdoptionHint":"Stetige Grundlast → Speicher 6–8 kWh","gridProcessNote":"5–8 Wochen","shadingRisk":"medium","roofMixNote":"Altbau + Neubau Mischstruktur"}
  ,{"slug":"mainz","insolationKwhM2":1185,"specificYieldRange":"950–1085","storageAdoptionHint":"Weinlagen Reflexion leicht positiv → Speicher 7–9 kWh","gridProcessNote":"4–6 Wochen","shadingRisk":"low","roofMixNote":"Steildächer mit geringer Verschattung"}
  ,{"slug":"muenster","insolationKwhM2":1045,"specificYieldRange":"870–980","storageAdoptionHint":"Wechselhaftes Wetter – Speicher 6–8 kWh stabilisiert","gridProcessNote":"6–9 Wochen","shadingRisk":"medium","roofMixNote":"Reihenhäuser + Vegetation"}
  ,{"slug":"nuernberg","insolationKwhM2":1160,"specificYieldRange":"935–1060","storageAdoptionHint":"Solide Einstrahlung – Speicher 7–9 kWh","gridProcessNote":"4–6 Wochen","shadingRisk":"low","roofMixNote":"Steildächer überwiegend frei"}
  ,{"slug":"saarbruecken","insolationKwhM2":1150,"specificYieldRange":"930–1050","storageAdoptionHint":"Grenznähe diffuses Licht – Speicher erhöht Eigenverbrauch","gridProcessNote":"5–8 Wochen","shadingRisk":"medium","roofMixNote":"Gemischte Dachtypen, teils Verschattung durch Bäume"}
]
